lambda_packages/__init__.py
lambda_packages/bcrypt/bcrypt-3.1.1.tar.gz
lambda_packages/cffi/cffi-1.7.0.tar.gz
lambda_packages/cryptography/cryptography-1.4.tar.gz
lambda_packages/datrie/datrie-0.7.2.tar.gz
lambda_packages/datrie_extended/datrie_extended-0.7.3.tar.gz
lambda_packages/lxml/lxml-3.6.0.tar.gz
lambda_packages/misaka/misaka-2.0.0.tar.gz
lambda_packages/MySQL-Python/MySQL-Python-1.2.5.tar.gz
lambda_packages/numpy/numpy-1.10.4.tar.gz
lambda_packages/OpenCV/OpenCV-3.1.0.tar.gz
lambda_packages/Pillow/Pillow-3.1.1.tar.gz
lambda_packages/Pillow/Pillow-3.4.2.tar.gz
lambda_packages/Pillow/test/test.py
lambda_packages/psycopg2/psycopg2-2.6.1.tar.gz
lambda_packages/pycrypto/pycrypto-2.6.1.tar.gz
lambda_packages/PyNaCl/PyNaCl-1.0.1.tar.gz
lambda_packages/pyproj/pyproj.4-4.9.2.tar.gz
lambda_packages/python-ldap/python-ldap-2.4.29.tar.gz
lambda_packages/python-Levenshtein/python-Levenshtein-0.12.0.tar.gz
lambda_packages/regex/regex-2016.8.27.tar.gz
lambda_packages-0.14.2.dist-info/DESCRIPTION.rst
lambda_packages-0.14.2.dist-info/METADATA
lambda_packages-0.14.2.dist-info/metadata.json
lambda_packages-0.14.2.dist-info/pbr.json
lambda_packages-0.14.2.dist-info/RECORD
lambda_packages-0.14.2.dist-info/top_level.txt
lambda_packages-0.14.2.dist-info/WHEEL
