Metadata-Version: 1.1
Name: lambda_packages
Version: 0.14.2
Summary: AWS Lambda Packages
Home-page: https://github.com/Miserlou/lambda-packages
Author: Rich Jones
Author-email: rich@openwatch.net
License: MIT License
Platform: UNKNOWN
Classifier: Environment :: Console
Classifier: License :: OSI Approved :: Apache Software License
Classifier: Operating System :: OS Independent
Classifier: Programming Language :: Python
Classifier: Programming Language :: Python :: 2.7
Classifier: Programming Language :: Python :: 3.3
Classifier: Programming Language :: Python :: 3.4
Classifier: Programming Language :: Python :: 3.5
Classifier: Topic :: Internet :: WWW/HTTP
Classifier: Topic :: Internet :: WWW/HTTP :: Dynamic Content
